jgTest_pkg/__init__.py
jgTest_pkg/test.py
mms_alice_testpackage-0.0.6.dist-info/LICENSE
mms_alice_testpackage-0.0.6.dist-info/METADATA
mms_alice_testpackage-0.0.6.dist-info/WHEEL
mms_alice_testpackage-0.0.6.dist-info/top_level.txt
mms_alice_testpackage-0.0.6.dist-info/RECORD
