Metadata-Version: 2.1
Name: mms-alice-testpackage
Version: 0.0.6
Summary: This is a test
Home-page: https://github.com/EastOfGondor/mms-alice-python-packages
Author: Josef Goppold
Author-email: goppold@mediamarktsaturn.com
License: UNKNOWN
Platform: UNKNOWN
Classifier: Programming Language :: Python :: 3
Classifier: License :: OSI Approved :: MIT License
Classifier: Operating System :: MacOS
